testlogic/Testgate2.v
/* Test2 회로 설계 */
module Testgate2(A, B,C, F);
  input A, B,C;
  output F;

  assign F=(A&B)|C;
endmodule

testlogic/tb_Testgate2.v
`timescale 1ns/10ps
/* Test2 게이트 Test2 Bench */
module tb_Testgate2;
  reg A,B,C;
  wire F;
  Testgate2 test2(A, B,C, F);

  //여기부터 waveform을 보기 위한 vcd 파일 작성 코드

  initial
    begin
      $dumpfile("test_Testgate2_out.vcd");
      $dumpvars(0,tb_Testgate2);
      $monitor("%b",F);
    end

    initial
      begin
        A=0; B=0; C=0; #100; //100ns 동안 시간 지연
        A=0; B=0; C=1; #100;
        A=0; B=1; C=0; #100;
        A=0; B=1; C=1; #100;
        A=1; B=0; C=0; #100;
        A=1; B=0; C=1; #100;
        A=1; B=1; C=0; #100;
        A=1; B=1; C=1; #100;

      end
endmodule

testlogic/test_Testgate2_out.vcd
$date
	Wed Oct 06 00:06:25 2021
$end
$version
	Icarus Verilog
$end
$timescale
	10ps
$end
$scope module tb_Testgate2 $end
$var wire 1 ! F $end
$var reg 1 " A $end
$var reg 1 # B $end
$var reg 1 $ C $end
$scope module test2 $end
$var wire 1 " A $end
$var wire 1 # B $end
$var wire 1 $ C $end
$var wire 1 ! F $end
$upscope $end
$upscope $end
$enddefinitions $end
#0
$dumpvars
0$
0#
0"
0!
$end
#10000
1!
1$
#20000
0!
0$
1#
#30000
1!
1$
#40000
0!
0$
0#
1"
#50000
1!
1$
#60000
0$
1#
#70000
1$
