testlogic/XORgate3.v
/* 3입력에 대한 XOR 회로 설계 */
module XORgate3(A, B, C, F);
  input A, B, C;
  output F;

  assign F = A^B^C;

endmodule

testlogic/tb_XORgate3.v
`timescale 1ns/10ps
module tb_XORgate3;
  reg A, B, C;
  wire F;
  XORgate3 XOR3(A, B, C, F);

  // 여기부터 waveform을 보기 위한 vcd 파일 작성 코드

  initial
    begin
      $dumpfile("test_XORgate3_out.vcd");
      $dumpvars(0, tb_XORgate3);
      $monitor("%b", F);
    end

    initial
      begin
        A=0; B=0; C=0; #100; //100ns 시간지연
        A=0; B=0; C=1; #100;
        A=0; B=1; C=0; #100;
        A=0; B=1; C=1; #100;
        A=1; B=0; C=0; #100;
        A=1; B=0; C=1; #100;
        A=1; B=1; C=0; #100;
        A=1; B=1; C=1; #100;
      end
endmodule

testlogic/test_XORgate3_out.vcd
$date
	Fri Oct 08 12:26:47 2021
$end
$version
	Icarus Verilog
$end
$timescale
	10ps
$end
$scope module tb_XORgate3 $end
$var wire 1 ! F $end
$var reg 1 " A $end
$var reg 1 # B $end
$var reg 1 $ C $end
$scope module XOR3 $end
$var wire 1 " A $end
$var wire 1 # B $end
$var wire 1 $ C $end
$var wire 1 ! F $end
$upscope $end
$upscope $end
$enddefinitions $end
#0
$dumpvars
0$
0#
0"
0!
$end
#10000
1!
1$
#20000
0$
1#
#30000
0!
1$
#40000
1!
0$
0#
1"
#50000
0!
1$
#60000
0$
1#
#70000
1!
1$
